{
  "timestamp": 1476527153,
  "data": [
    {
      "QNH_iHg": "",
      "planned_deptime": "",
      "planned_destairport_lon": "",
      "planned_altitude": "",
      "time_last_atis_received": "20161015232339",
      "planned_hrsfuel": "",
      "rating": "11",
      "planned_depairport": "",
      "realname": "Andrew Heath",
      "planned_minenroute": "",
      "protrevision": "100",
      "planned_remarks": "",
      "atis_message": "New York Center^\u00a7Serving all ZNY sectors including PHL TRACON (no oceanic)^\u00a7Class D tower services provided workload permitting^\u00a7Pilot Resources - nyartcc.org",
      "planned_route": "",
      "planned_tascruise": "0",
      "callsign": "AJ_SUP",
      "transponder": "",
      "heading": "",
      "clienttype": "ATC",
      "visualrange": "300",
      "latitude": "40.63590",
      "planned_minfuel": "",
      "facilitytype": "0",
      "planned_hrsenroute": "",
      "planned_aircraft": "",
      "longitude": "-73.75422",
      "frequency": "199.998",
      "time_logon": "20161015230817",
      "planned_destairport": "",
      "groundspeed": "",
      "planned_flighttype": "",
      "planned_depairport_lat": "",
      "altitude": "0",
      "planned_altairport": "",
      "server": "USA-E",
      "cid": "810253",
      "planned_destairport_lat": "",
      "QNH_Mb": "",
      "planned_depairport_lon": "",
      "planned_actdeptime": "",
      "planned_revision": ""
    },
    {
      "QNH_iHg": "",
      "planned_deptime": "",
      "planned_destairport_lon": "",
      "planned_altitude": "",
      "time_last_atis_received": "20161015232434",
      "planned_hrsfuel": "",
      "rating": "10",
      "planned_depairport": "",
      "realname": "Evan Reiter",
      "planned_minenroute": "",
      "protrevision": "100",
      "planned_remarks": "",
      "atis_message": "$ voice.bvartcc.com/ZBW_134.700^\u00a7CTR will be staffed until 10 00pm ET or later^\u00a7Read our Letter to Airmen at bvartcc.com/LTA^\u00a7See planned ATC availability at bvartcc.com/Timetable^\u00a7Boston Virtual ARTCC is an integrated pilot and ATC community^\u00a7Visit www.bvartcc.com to apply",
      "planned_route": "",
      "planned_tascruise": "0",
      "callsign": "BOS_CTR",
      "transponder": "",
      "heading": "",
      "clienttype": "ATC",
      "visualrange": "360",
      "latitude": "43.35627",
      "planned_minfuel": "",
      "facilitytype": "6",
      "planned_hrsenroute": "",
      "planned_aircraft": "",
      "longitude": "-70.74112",
      "frequency": "134.700",
      "time_logon": "20161015212247",
      "planned_destairport": "",
      "groundspeed": "",
      "planned_flighttype": "",
      "planned_depairport_lat": "",
      "altitude": "0",
      "planned_altairport": "",
      "server": "USA-E",
      "cid": "1314720",
      "planned_destairport_lat": "",
      "QNH_Mb": "",
      "planned_depairport_lon": "",
      "planned_actdeptime": "",
      "planned_revision": ""
    },
    {
      "QNH_iHg": "",
      "planned_deptime": "",
      "planned_destairport_lon": "",
      "planned_altitude": "",
      "time_last_atis_received": "20161015232059",
      "planned_hrsfuel": "",
      "rating": "7",
      "planned_depairport": "",
      "realname": "Tomas Hansson",
      "planned_minenroute": "",
      "protrevision": "100",
      "planned_remarks": "",
      "atis_message": "$ canada.voice.vatsim.net/cyvr_atis^\u00a7CYVR information B weather at 2300Z , Wind 060 at 22 gusting 33^\u00a7, Visibility 15 , Sky conditions 4000 scattered 5600 broken^\u00a77000 broken temperature 13 dew point 8 , Altimeter 2904 ,^\u00a7Approach ils runway 08L , Departure runway 08R ,^\u00a7Advise ATC that you have information B .",
      "planned_route": "",
      "planned_tascruise": "0",
      "callsign": "CYVR_ATIS",
      "transponder": "",
      "heading": "",
      "clienttype": "ATC",
      "visualrange": "0",
      "latitude": "49.19469",
      "planned_minfuel": "",
      "facilitytype": "4",
      "planned_hrsenroute": "",
      "planned_aircraft": "",
      "longitude": "-123.18397",
      "frequency": "124.600",
      "time_logon": "20161015223522",
      "planned_destairport": "",
      "groundspeed": "",
      "planned_flighttype": "",
      "planned_depairport_lat": "",
      "altitude": "0",
      "planned_altairport": "",
      "server": "CANADA",
      "cid": "840812",
      "planned_destairport_lat": "",
      "QNH_Mb": "",
      "planned_depairport_lon": "",
      "planned_actdeptime": "",
      "planned_revision": ""
    },
    {
      "QNH_iHg": "",
      "planned_deptime": "",
      "planned_destairport_lon": "",
      "planned_altitude": "",
      "time_last_atis_received": "20161015231613",
      "planned_hrsfuel": "",
      "rating": "2",
      "planned_depairport": "",
      "realname": "Matthew Nasseri",
      "planned_minenroute": "",
      "protrevision": "100",
      "planned_remarks": "",
      "atis_message": "$ canada.voice.vatsim.net/cyvr_gnd^\u00a7Charts and info at www.CZVR.ca^\u00a7Callsign = Vancouver Ground",
      "planned_route": "",
      "planned_tascruise": "0",
      "callsign": "CYVR_GND",
      "transponder": "",
      "heading": "",
      "clienttype": "ATC",
      "visualrange": "20",
      "latitude": "49.19484",
      "planned_minfuel": "",
      "facilitytype": "3",
      "planned_hrsenroute": "",
      "planned_aircraft": "",
      "longitude": "-123.17833",
      "frequency": "121.700",
      "time_logon": "20161015224522",
      "planned_destairport": "",
      "groundspeed": "",
      "planned_flighttype": "",
      "planned_depairport_lat": "",
      "altitude": "0",
      "planned_altairport": "",
      "server": "USA-E",
      "cid": "1360046",
      "planned_destairport_lat": "",
      "QNH_Mb": "",
      "planned_depairport_lon": "",
      "planned_actdeptime": "",
      "planned_revision": ""
    },
    {
      "QNH_iHg": "",
      "planned_deptime": "",
      "planned_destairport_lon": "",
      "planned_altitude": "",
      "time_last_atis_received": "20161015231914",
      "planned_hrsfuel": "",
      "rating": "7",
      "planned_depairport": "",
      "realname": "Tomas Hansson",
      "planned_minenroute": "",
      "protrevision": "100",
      "planned_remarks": "",
      "atis_message": "$ canada.voice.vatsim.net/czvr_ctr^\u00a7Charts and info at czvr.vatcan.ca^\u00a7Callsign = Vancouver Centre",
      "planned_route": "",
      "planned_tascruise": "0",
      "callsign": "CZVR_CTR",
      "transponder": "",
      "heading": "",
      "clienttype": "ATC",
      "visualrange": "300",
      "latitude": "48.61204",
      "planned_minfuel": "",
      "facilitytype": "6",
      "planned_hrsenroute": "",
      "planned_aircraft": "",
      "longitude": "-123.44390",
      "frequency": "133.700",
      "time_logon": "20161015223348",
      "planned_destairport": "",
      "groundspeed": "",
      "planned_flighttype": "",
      "planned_depairport_lat": "",
      "altitude": "0",
      "planned_altairport": "",
      "server": "CANADA",
      "cid": "840812",
      "planned_destairport_lat": "",
      "QNH_Mb": "",
      "planned_depairport_lon": "",
      "planned_actdeptime": "",
      "planned_revision": ""
    },
    {
      "QNH_iHg": "",
      "planned_deptime": "",
      "planned_destairport_lon": "",
      "planned_altitude": "",
      "time_last_atis_received": "20161015232152",
      "planned_hrsfuel": "",
      "rating": "2",
      "planned_depairport": "",
      "realname": "Jaden Simmons",
      "planned_minenroute": "",
      "protrevision": "100",
      "planned_remarks": "",
      "atis_message": "$ rw.liveatc.net/DEN_GND^\u00a7denartcc.org/feedback",
      "planned_route": "",
      "planned_tascruise": "0",
      "callsign": "DEN_GND",
      "transponder": "",
      "heading": "",
      "clienttype": "ATC",
      "visualrange": "20",
      "latitude": "39.85673",
      "planned_minfuel": "",
      "facilitytype": "3",
      "planned_hrsenroute": "",
      "planned_aircraft": "",
      "longitude": "-104.66147",
      "frequency": "121.850",
      "time_logon": "20161015225103",
      "planned_destairport": "",
      "groundspeed": "",
      "planned_flighttype": "",
      "planned_depairport_lat": "",
      "altitude": "0",
      "planned_altairport": "",
      "server": "USA-W",
      "cid": "1323903",
      "planned_destairport_lat": "",
      "QNH_Mb": "",
      "planned_depairport_lon": "",
      "planned_actdeptime": "",
      "planned_revision": ""
    },
    {
      "QNH_iHg": "",
      "planned_deptime": "",
      "planned_destairport_lon": "",
      "planned_altitude": "",
      "time_last_atis_received": "20161015231638",
      "planned_hrsfuel": "",
      "rating": "5",
      "planned_depairport": "",
      "realname": "Robin Karthaeuser",
      "planned_minenroute": "",
      "protrevision": "100",
      "planned_remarks": "",
      "atis_message": "$ voice1.vacc-sag.org/edbb_n_app^\u00a7This is BREMEN RADAR, the arrival of BERLIN^\u00a7ATIS for Berlin Tegel on 125.900 and Berlin Schoenefeld on 124.950",
      "planned_route": "",
      "planned_tascruise": "0",
      "callsign": "EDBB_N_APP",
      "transponder": "",
      "heading": "",
      "clienttype": "ATC",
      "visualrange": "123",
      "latitude": "52.48009",
      "planned_minfuel": "",
      "facilitytype": "5",
      "planned_hrsenroute": "",
      "planned_aircraft": "",
      "longitude": "13.38744",
      "frequency": "119.620",
      "time_logon": "20161015195821",
      "planned_destairport": "",
      "groundspeed": "",
      "planned_flighttype": "",
      "planned_depairport_lat": "",
      "altitude": "0",
      "planned_altairport": "",
      "server": "GERMANY",
      "cid": "1169225",
      "planned_destairport_lat": "",
      "QNH_Mb": "",
      "planned_depairport_lon": "",
      "planned_actdeptime": "",
      "planned_revision": ""
    },
    {
      "QNH_iHg": "",
      "planned_deptime": "",
      "planned_destairport_lon": "",
      "planned_altitude": "",
      "time_last_atis_received": "20161015231704",
      "planned_hrsfuel": "",
      "rating": "5",
      "planned_depairport": "",
      "realname": "Robin Karthaeuser",
      "planned_minenroute": "",
      "protrevision": "100",
      "planned_remarks": "",
      "atis_message": "$ voice1.vacc-sag.org/eddb_atis^\u00a7BERLIN SCHOENEFELD INFORMATION LIMA   MET REPORT TIME 2250  ^\u00a7EXPECT ILS APPROACH RUNWAY IN USE 07L   DEPARTURE FREQUENCY^\u00a7119.62   TRL 60   WIND 080 DEGREES 8 KNOTS   VISIBILITY 2200^\u00a7METERS   PRESENT WEATHER MIST   CLOUDS OVERCAST 200 FT  ^\u00a7TEMPERATURE 8   DEWPOINT 8   QNH 1020 HPA   INFORMATION LIMA^\u00a7OUT      ",
      "planned_route": "",
      "planned_tascruise": "0",
      "callsign": "EDDB_ATIS",
      "transponder": "",
      "heading": "",
      "clienttype": "ATC",
      "visualrange": "0",
      "latitude": "52.36225",
      "planned_minfuel": "",
      "facilitytype": "4",
      "planned_hrsenroute": "",
      "planned_aircraft": "",
      "longitude": "13.50067",
      "frequency": "124.950",
      "time_logon": "20161015195917",
      "planned_destairport": "",
      "groundspeed": "",
      "planned_flighttype": "",
      "planned_depairport_lat": "",
      "altitude": "0",
      "planned_altairport": "",
      "server": "GERMANY",
      "cid": "1169225",
      "planned_destairport_lat": "",
      "QNH_Mb": "",
      "planned_depairport_lon": "",
      "planned_actdeptime": "",
      "planned_revision": ""
    },
    {
      "QNH_iHg": "",
      "planned_deptime": "",
      "planned_destairport_lon": "",
      "planned_altitude": "",
      "time_last_atis_received": "20161015231848",
      "planned_hrsfuel": "",
      "rating": "3",
      "planned_depairport": "",
      "realname": "Marius Gebauer",
      "planned_minenroute": "",
      "protrevision": "100",
      "planned_remarks": "",
      "atis_message": "$ voice1.vacc-sag.org/eddt_atis^\u00a7BERLIN TEGEL INFORMATION V MET REPORT TIME 2250    ^\u00a7EXPECT ILS APPROACH     RUNWAY 08L     RUNWAYS IN USE 08L AND^\u00a708R     FOR DEPARTURE EXPECT RUNWAY 08R RUNWAY 08L ON REQUEST^\u00a7    TRANSITION LEVEL 60^\u00a7USE CAUTION AFTER LANDING SHORT DISTANCE BETWEEN RUNWAYS EXPECT TO STOP BEFORE PARALLEL RUNWAY^\u00a7    DEPARTURE FREQUENCY BREMEN RADAR ON FREQUENCY 119.625    ^\u00a7WIND 080 DEGREES 4 KNOTS VARIABLE BETWEEN 040 AND 130 DEGREES^\u00a7    VISIBILITY 3400 METERS     mist     CLOUDS BROKEN 300 FEET^\u00a7    TEMPERATURE 9 DEW POINT 8     QNH 1020^\u00a7ADVISE ON INITIAL CONTACT YOU HAVE INFORMATION V    ",
      "planned_route": "",
      "planned_tascruise": "0",
      "callsign": "EDDT_ATIS",
      "transponder": "",
      "heading": "",
      "clienttype": "ATC",
      "visualrange": "0",
      "latitude": "52.56000",
      "planned_minfuel": "",
      "facilitytype": "4",
      "planned_hrsenroute": "",
      "planned_aircraft": "",
      "longitude": "13.28833",
      "frequency": "125.900",
      "time_logon": "20161015191555",
      "planned_destairport": "",
      "groundspeed": "",
      "planned_flighttype": "",
      "planned_depairport_lat": "",
      "altitude": "0",
      "planned_altairport": "",
      "server": "SWEDEN",
      "cid": "1138043",
      "planned_destairport_lat": "",
      "QNH_Mb": "",
      "planned_depairport_lon": "",
      "planned_actdeptime": "",
      "planned_revision": ""
    },
    {
      "QNH_iHg": "",
      "planned_deptime": "",
      "planned_destairport_lon": "",
      "planned_altitude": "",
      "time_last_atis_received": "20161015231546",
      "planned_hrsfuel": "",
      "rating": "3",
      "planned_depairport": "",
      "realname": "Marius Gebauer",
      "planned_minenroute": "",
      "protrevision": "100",
      "planned_remarks": "",
      "atis_message": "$ voice1.vacc-sag.org/eddt_twr^\u00a7TEGEL TOWER^\u00a7Monitor ATIS on 125.900",
      "planned_route": "",
      "planned_tascruise": "0",
      "callsign": "EDDT_TWR",
      "transponder": "",
      "heading": "",
      "clienttype": "ATC",
      "visualrange": "40",
      "latitude": "52.56000",
      "planned_minfuel": "",
      "facilitytype": "4",
      "planned_hrsenroute": "",
      "planned_aircraft": "",
      "longitude": "13.28833",
      "frequency": "124.520",
      "time_logon": "20161015191225",
      "planned_destairport": "",
      "groundspeed": "",
      "planned_flighttype": "",
      "planned_depairport_lat": "",
      "altitude": "0",
      "planned_altairport": "",
      "server": "SWEDEN",
      "cid": "1138043",
      "planned_destairport_lat": "",
      "QNH_Mb": "",
      "planned_depairport_lon": "",
      "planned_actdeptime": "",
      "planned_revision": ""
    },
    {
      "QNH_iHg": "",
      "planned_deptime": "",
      "planned_destairport_lon": "",
      "planned_altitude": "",
      "time_last_atis_received": "20161015231638",
      "planned_hrsfuel": "",
      "rating": "4",
      "planned_depairport": "",
      "realname": "RICHARD KEEN",
      "planned_minenroute": "",
      "protrevision": "100",
      "planned_remarks": "",
      "atis_message": "$ uk.voice.vatsim.net/egkk_app^\u00a7Gatwick Director^\u00a7Voice ATIS on 134.225^\u00a7Charts at tinyurl.com/kkcharts",
      "planned_route": "",
      "planned_tascruise": "0",
      "callsign": "EGKK_APP",
      "transponder": "",
      "heading": "",
      "clienttype": "ATC",
      "visualrange": "141",
      "latitude": "51.14806",
      "planned_minfuel": "",
      "facilitytype": "5",
      "planned_hrsenroute": "",
      "planned_aircraft": "",
      "longitude": "-0.19028",
      "frequency": "126.820",
      "time_logon": "20161015221507",
      "planned_destairport": "",
      "groundspeed": "",
      "planned_flighttype": "",
      "planned_depairport_lat": "",
      "altitude": "0",
      "planned_altairport": "",
      "server": "UK1",
      "cid": "937253",
      "planned_destairport_lat": "",
      "QNH_Mb": "",
      "planned_depairport_lon": "",
      "planned_actdeptime": "",
      "planned_revision": ""
    },
    {
      "QNH_iHg": "",
      "planned_deptime": "",
      "planned_destairport_lon": "",
      "planned_altitude": "",
      "time_last_atis_received": "20161015232312",
      "planned_hrsfuel": "",
      "rating": "4",
      "planned_depairport": "",
      "realname": "RICHARD KEEN",
      "planned_minenroute": "",
      "protrevision": "100",
      "planned_remarks": "",
      "atis_message": "$ uk.voice.vatsim.net/egkk_atis^\u00a7Gatwick information X Time 225 0, Runway in use 26L^\u00a7Surface wind 14 0, 3 knots Visibility 10km or more shallow fog^\u00a7few 3200 feet Temperature + 7, Dew point + 7, QNH 101 1,^\u00a7Acknowledge receipt of information X and advise aircraft type^\u00a7on first contact",
      "planned_route": "",
      "planned_tascruise": "0",
      "callsign": "EGKK_ATIS",
      "transponder": "",
      "heading": "",
      "clienttype": "ATC",
      "visualrange": "0",
      "latitude": "51.14806",
      "planned_minfuel": "",
      "facilitytype": "4",
      "planned_hrsenroute": "",
      "planned_aircraft": "",
      "longitude": "-0.19028",
      "frequency": "134.220",
      "time_logon": "20161015222236",
      "planned_destairport": "",
      "groundspeed": "",
      "planned_flighttype": "",
      "planned_depairport_lat": "",
      "altitude": "0",
      "planned_altairport": "",
      "server": "UK1",
      "cid": "937253",
      "planned_destairport_lat": "",
      "QNH_Mb": "",
      "planned_depairport_lon": "",
      "planned_actdeptime": "",
      "planned_revision": ""
    },
    {
      "QNH_iHg": "",
      "planned_deptime": "",
      "planned_destairport_lon": "",
      "planned_altitude": "",
      "time_last_atis_received": "20161015232526",
      "planned_hrsfuel": "",
      "rating": "3",
      "planned_depairport": "",
      "realname": "Dave Ramsey",
      "planned_minenroute": "",
      "protrevision": "100",
      "planned_remarks": "",
      "atis_message": "$ uk2.voice.vatsim.net/egss_atis^\u00a7Stansted information N Time 225 0, automatic Runway in use 2^\u00a72, Transition Level Flight Level 6 5,^\u00a7ILS Approach to be Expected Surface wind 19 0, 7 knots^\u00a7Visibility 10km or more No cloud detected Temperature +1 0,^\u00a7Dew point + 9, QNH 101 1, Acknowledge receipt of information N^\u00a7and advise aircraft type on first contact",
      "planned_route": "",
      "planned_tascruise": "0",
      "callsign": "EGSS_ATIS",
      "transponder": "",
      "heading": "",
      "clienttype": "ATC",
      "visualrange": "0",
      "latitude": "51.88500",
      "planned_minfuel": "",
      "facilitytype": "4",
      "planned_hrsenroute": "",
      "planned_aircraft": "",
      "longitude": "0.23500",
      "frequency": "127.170",
      "time_logon": "20161015223944",
      "planned_destairport": "",
      "groundspeed": "",
      "planned_flighttype": "",
      "planned_depairport_lat": "",
      "altitude": "0",
      "planned_altairport": "",
      "server": "UK1",
      "cid": "1280218",
      "planned_destairport_lat": "",
      "QNH_Mb": "",
      "planned_depairport_lon": "",
      "planned_actdeptime": "",
      "planned_revision": ""
    },
    {
      "QNH_iHg": "",
      "planned_deptime": "",
      "planned_destairport_lon": "",
      "planned_altitude": "",
      "time_last_atis_received": "20161015232500",
      "planned_hrsfuel": "",
      "rating": "3",
      "planned_depairport": "",
      "realname": "Dave Ramsey",
      "planned_minenroute": "",
      "protrevision": "100",
      "planned_remarks": "",
      "atis_message": "$ uk2.voice.vatsim.net/egss_twr^\u00a7Stansted Tower^\u00a7Voice ATIS on 127.170^\u00a7NOTAM LAM Departure for Flights to EGLL Only!",
      "planned_route": "",
      "planned_tascruise": "0",
      "callsign": "EGSS_TWR",
      "transponder": "",
      "heading": "",
      "clienttype": "ATC",
      "visualrange": "50",
      "latitude": "51.88500",
      "planned_minfuel": "",
      "facilitytype": "4",
      "planned_hrsenroute": "",
      "planned_aircraft": "",
      "longitude": "0.23500",
      "frequency": "123.800",
      "time_logon": "20161015223905",
      "planned_destairport": "",
      "groundspeed": "",
      "planned_flighttype": "",
      "planned_depairport_lat": "",
      "altitude": "0",
      "planned_altairport": "",
      "server": "UK1",
      "cid": "1280218",
      "planned_destairport_lat": "",
      "QNH_Mb": "",
      "planned_depairport_lon": "",
      "planned_actdeptime": "",
      "planned_revision": ""
    },
    {
      "QNH_iHg": "",
      "planned_deptime": "",
      "planned_destairport_lon": "",
      "planned_altitude": "",
      "time_last_atis_received": "20161015231040",
      "planned_hrsfuel": "",
      "rating": "5",
      "planned_depairport": "",
      "realname": "Jan Tore Elvheim",
      "planned_minenroute": "",
      "protrevision": "100",
      "planned_remarks": "",
      "atis_message": "$ voice.vatsim-scandinavia.org/ensg_i_twr^\u00a7Sogndal Information",
      "planned_route": "",
      "planned_tascruise": "0",
      "callsign": "ENSG_I_TWR",
      "transponder": "",
      "heading": "",
      "clienttype": "ATC",
      "visualrange": "25",
      "latitude": "61.38556",
      "planned_minfuel": "",
      "facilitytype": "4",
      "planned_hrsenroute": "",
      "planned_aircraft": "",
      "longitude": "5.76311",
      "frequency": "119.300",
      "time_logon": "20161015203842",
      "planned_destairport": "",
      "groundspeed": "",
      "planned_flighttype": "",
      "planned_depairport_lat": "",
      "altitude": "0",
      "planned_altairport": "",
      "server": "UK2",
      "cid": "835974",
      "planned_destairport_lat": "",
      "QNH_Mb": "",
      "planned_depairport_lon": "",
      "planned_actdeptime": "",
      "planned_revision": ""
    },
    {
      "QNH_iHg": "",
      "planned_deptime": "",
      "planned_destairport_lon": "",
      "planned_altitude": "",
      "time_last_atis_received": "20161015231704",
      "planned_hrsfuel": "",
      "rating": "2",
      "planned_depairport": "",
      "realname": "William van Aller",
      "planned_minenroute": "",
      "protrevision": "100",
      "planned_remarks": "",
      "atis_message": "This is Troms\u00f8 information C time 2250 expect ils approach^\u00a7runway in use 19 transition level 80 wind 210 degrees 10 knots^\u00a7visibility more than 10 kilometers broken 2900 feet^\u00a7temperature 5 dew point 2 QNH 1029 Acknowledge information C",
      "planned_route": "",
      "planned_tascruise": "0",
      "callsign": "ENTC_ATIS",
      "transponder": "",
      "heading": "",
      "clienttype": "ATC",
      "visualrange": "0",
      "latitude": "69.68139",
      "planned_minfuel": "",
      "facilitytype": "4",
      "planned_hrsenroute": "",
      "planned_aircraft": "",
      "longitude": "18.91778",
      "frequency": "199.998",
      "time_logon": "20161015230137",
      "planned_destairport": "",
      "groundspeed": "",
      "planned_flighttype": "",
      "planned_depairport_lat": "",
      "altitude": "0",
      "planned_altairport": "",
      "server": "SWEDEN",
      "cid": "1298664",
      "planned_destairport_lat": "",
      "QNH_Mb": "",
      "planned_depairport_lon": "",
      "planned_actdeptime": "",
      "planned_revision": ""
    },
    {
      "QNH_iHg": "",
      "planned_deptime": "",
      "planned_destairport_lon": "",
      "planned_altitude": "",
      "time_last_atis_received": "20161015232434",
      "planned_hrsfuel": "",
      "rating": "2",
      "planned_depairport": "",
      "realname": "William van Aller",
      "planned_minenroute": "",
      "protrevision": "100",
      "planned_remarks": "",
      "atis_message": "$ voice.vatsim-scandinavia.org/entc_twr^\u00a7Troms\u00f8 Tower^\u00a7Voice ATIS available on 126.125",
      "planned_route": "",
      "planned_tascruise": "0",
      "callsign": "ENTC_TWR",
      "transponder": "",
      "heading": "",
      "clienttype": "ATC",
      "visualrange": "48",
      "latitude": "69.64125",
      "planned_minfuel": "",
      "facilitytype": "4",
      "planned_hrsenroute": "",
      "planned_aircraft": "",
      "longitude": "16.76117",
      "frequency": "118.300",
      "time_logon": "20161015223836",
      "planned_destairport": "",
      "groundspeed": "",
      "planned_flighttype": "",
      "planned_depairport_lat": "",
      "altitude": "0",
      "planned_altairport": "",
      "server": "SWEDEN",
      "cid": "1298664",
      "planned_destairport_lat": "",
      "QNH_Mb": "",
      "planned_depairport_lon": "",
      "planned_actdeptime": "",
      "planned_revision": ""
    },
    {
      "QNH_iHg": "",
      "planned_deptime": "",
      "planned_destairport_lon": "",
      "planned_altitude": "",
      "time_last_atis_received": "20161015232527",
      "planned_hrsfuel": "",
      "rating": "2",
      "planned_depairport": "",
      "realname": "Tristan Proctor",
      "planned_minenroute": "",
      "protrevision": "100",
      "planned_remarks": "",
      "atis_message": "$ voice.zmaartcc.net/FLL_GND",
      "planned_route": "",
      "planned_tascruise": "0",
      "callsign": "FLL_GND",
      "transponder": "",
      "heading": "",
      "clienttype": "ATC",
      "visualrange": "20",
      "latitude": "26.07421",
      "planned_minfuel": "",
      "facilitytype": "3",
      "planned_hrsenroute": "",
      "planned_aircraft": "",
      "longitude": "-80.14860",
      "frequency": "121.400",
      "time_logon": "20161015232506",
      "planned_destairport": "",
      "groundspeed": "",
      "planned_flighttype": "",
      "planned_depairport_lat": "",
      "altitude": "0",
      "planned_altairport": "",
      "server": "USA-C2",
      "cid": "1165032",
      "planned_destairport_lat": "",
      "QNH_Mb": "",
      "planned_depairport_lon": "",
      "planned_actdeptime": "",
      "planned_revision": ""
    },
    {
      "QNH_iHg": "",
      "planned_deptime": "",
      "planned_destairport_lon": "",
      "planned_altitude": "",
      "time_last_atis_received": "20161015232059",
      "planned_hrsfuel": "",
      "rating": "3",
      "planned_depairport": "",
      "realname": "Joseph Jucha",
      "planned_minenroute": "",
      "protrevision": "100",
      "planned_remarks": "",
      "atis_message": "$ rw.liveatc.net/IND_TWR^\u00a7Indianapolis Tower^\u00a7Welcome to IND!^\u00a7I expect to be on on untill 0400Z^\u00a7Please let me know if you read this",
      "planned_route": "",
      "planned_tascruise": "0",
      "callsign": "IND_TWR",
      "transponder": "",
      "heading": "",
      "clienttype": "ATC",
      "visualrange": "30",
      "latitude": "39.71824",
      "planned_minfuel": "",
      "facilitytype": "4",
      "planned_hrsenroute": "",
      "planned_aircraft": "",
      "longitude": "-86.29091",
      "frequency": "120.900",
      "time_logon": "20161015223511",
      "planned_destairport": "",
      "groundspeed": "",
      "planned_flighttype": "",
      "planned_depairport_lat": "",
      "altitude": "0",
      "planned_altairport": "",
      "server": "USA-C",
      "cid": "1343412",
      "planned_destairport_lat": "",
      "QNH_Mb": "",
      "planned_depairport_lon": "",
      "planned_actdeptime": "",
      "planned_revision": ""
    },
    {
      "QNH_iHg": "",
      "planned_deptime": "",
      "planned_destairport_lon": "",
      "planned_altitude": "",
      "time_last_atis_received": "20161015232218",
      "planned_hrsfuel": "",
      "rating": "2",
      "planned_depairport": "",
      "realname": "Sam Messervy",
      "planned_minenroute": "",
      "protrevision": "100",
      "planned_remarks": "",
      "atis_message": "$ voice.nyartcc.org/ZNY_3D^\u00a7Long Island Ground^\u00a7Information (None) Winds 170 at 4 Vis 10SM Sky FEW040 BKN260 Alt 3035^\u00a7Pilot Resources www.nyartcc.org",
      "planned_route": "",
      "planned_tascruise": "0",
      "callsign": "ISP_GND",
      "transponder": "",
      "heading": "",
      "clienttype": "ATC",
      "visualrange": "20",
      "latitude": "40.79444",
      "planned_minfuel": "",
      "facilitytype": "3",
      "planned_hrsenroute": "",
      "planned_aircraft": "",
      "longitude": "-73.10111",
      "frequency": "135.300",
      "time_logon": "20161015213556",
      "planned_destairport": "",
      "groundspeed": "",
      "planned_flighttype": "",
      "planned_depairport_lat": "",
      "altitude": "0",
      "planned_altairport": "",
      "server": "USA-E",
      "cid": "1349327",
      "planned_destairport_lat": "",
      "QNH_Mb": "",
      "planned_depairport_lon": "",
      "planned_actdeptime": "",
      "planned_revision": ""
    },
    {
      "QNH_iHg": "",
      "planned_deptime": "",
      "planned_destairport_lon": "",
      "planned_altitude": "",
      "time_last_atis_received": "20161015232527",
      "planned_hrsfuel": "",
      "rating": "10",
      "planned_depairport": "",
      "realname": "Evan Reiter",
      "planned_minenroute": "",
      "protrevision": "100",
      "planned_remarks": "",
      "atis_message": "$ voice.bvartcc.com/KBOS_ATIS^\u00a7BOSTON LOGAN AIRPORT INFO S 2254Z 16009KT 10SM FEW250 BKN300^\u00a711/06 A3037 (THREE ZERO THREE SEVEN). ... ILS RUNWAY 4R APPROACH^\u00a7IN USE. DEPARTING RUNWAY 9. RUNWAY 4L-22R CLOSED, NOT AVAILABLE^\u00a7FOR TAXI. ALL AIRCRAFT READBACK ALL HOLD SHORT INSTRUCTIONS AND^\u00a7ASSIGNED ALTITUDES. MODERATE BIRD ACTIVITY IN ALL AREAS.^\u00a7HAZARDOUS WEATHER INFORMATION FOR NEW ENGLAND AREA AVAILABLE^\u00a7FROM ATC ON REQUEST. NUMEROUS CONSTRUCTION CRANES IN THE BOSTON^\u00a7AREA AND IN THE VICINITY OF LOGAN AIRPORT. ...ADVISE ON INITIAL^\u00a7CONTACT YOU HAVE INFO S",
      "planned_route": "",
      "planned_tascruise": "0",
      "callsign": "KBOS_ATIS",
      "transponder": "",
      "heading": "",
      "clienttype": "ATC",
      "visualrange": "0",
      "latitude": "42.36296",
      "planned_minfuel": "",
      "facilitytype": "4",
      "planned_hrsenroute": "",
      "planned_aircraft": "",
      "longitude": "-71.00643",
      "frequency": "135.000",
      "time_logon": "20161015212322",
      "planned_destairport": "",
      "groundspeed": "",
      "planned_flighttype": "",
      "planned_depairport_lat": "",
      "altitude": "0",
      "planned_altairport": "",
      "server": "USA-E",
      "cid": "1314720",
      "planned_destairport_lat": "",
      "QNH_Mb": "",
      "planned_depairport_lon": "",
      "planned_actdeptime": "",
      "planned_revision": ""
    },
    {
      "QNH_iHg": "",
      "planned_deptime": "",
      "planned_destairport_lon": "",
      "planned_altitude": "",
      "time_last_atis_received": "20161015232125",
      "planned_hrsfuel": "",
      "rating": "3",
      "planned_depairport": "",
      "realname": "Joseph Jucha",
      "planned_minenroute": "",
      "protrevision": "100",
      "planned_remarks": "",
      "atis_message": "$ rw.liveatc.net/KIND_ATIS^\u00a7IND ATIS INFO B 2254Z. 18008KT 10SM FEW034 FEW250 22/16 A3006^\u00a7(THREE ZERO ZERO SIX). LDG AND DEPTG RWYS 23L AND 23R. SIMUL^\u00a7DEPS IN USE. SIMUL VIS AND LOC APCHS IN USE.... NOTAMS... NEW^\u00a7MIDFIELD TERMINAL SCENERY AVBL. ON INITIAL CONTACT, ADVS HAVING^\u00a7NEW MIDFIELD TERMINAL OR DEFAULT NE RAMP SCENERY. PRE-DEP^\u00a7CLEARANCES ARE AVBL. HAZD WX INFO FOR KIND IS AVBL ON RQST. OPER^\u00a7XPDR IN MODE C ON ALL TWYS AND RWYS, READ BACK ALL HS^\u00a7INSTRUCTIONS, VFR ACFT SAY DIRECTION OF FLIGHT. ADVS YOU HAVE^\u00a7INFO B.",
      "planned_route": "",
      "planned_tascruise": "0",
      "callsign": "KIND_ATIS",
      "transponder": "",
      "heading": "",
      "clienttype": "ATC",
      "visualrange": "0",
      "latitude": "39.71730",
      "planned_minfuel": "",
      "facilitytype": "4",
      "planned_hrsenroute": "",
      "planned_aircraft": "",
      "longitude": "-86.29466",
      "frequency": "134.250",
      "time_logon": "20161015223535",
      "planned_destairport": "",
      "groundspeed": "",
      "planned_flighttype": "",
      "planned_depairport_lat": "",
      "altitude": "0",
      "planned_altairport": "",
      "server": "USA-C",
      "cid": "1343412",
      "planned_destairport_lat": "",
      "QNH_Mb": "",
      "planned_depairport_lon": "",
      "planned_actdeptime": "",
      "planned_revision": ""
    },
    {
      "QNH_iHg": "",
      "planned_deptime": "",
      "planned_destairport_lon": "",
      "planned_altitude": "",
      "time_last_atis_received": "20161015232059",
      "planned_hrsfuel": "",
      "rating": "3",
      "planned_depairport": "",
      "realname": "Ryan Biehl",
      "planned_minenroute": "",
      "protrevision": "100",
      "planned_remarks": "",
      "atis_message": "$ vhf.laartcc.org/KLAX_ATIS^\u00a7LAX ATIS INFO D 2253Z. 26011KT 10SM BKN015 21/16 A2995 (TWO^\u00a7NINER NINER FIVE). SIMUL INST APCHS IN PROG TO RWYS 24R AND 25L,^\u00a7OR VCTR FOR VISUAL APCH WILL BE PROVIDED, SIMUL VISUAL APCHS TO^\u00a7ALL RWYS ARE IN PROG, AND SIMUL APCHS IN PROG BTWN LAX AND HHR,^\u00a7SIMUL INSTR DEPARTURES IN PROG RWYS 24 AND 25. CTC L A GC ON^\u00a7121.4 FOR PUSH ON TAXILANE S AND PUSH OR TAXI ON A. NOTAMS...^\u00a7RWY 2 4 LEFT 6 RIGHT CLSD. TWY B CLSD BTN TWY, F AND TWY J TWY E^\u00a7CLSD BTN TWY E15 AND TWY E17, TAXIWAY ECHO CLOSED BETWEEN^\u00a7TAXIWAY ECHO SIX AND DELTA SEVEN. ILS RY 25R OTS. CRANES^\u00a7AFFECTING RWY 24R ARE DOWN. CRANES AFFECTING RWY 25L ARE DOWN.^\u00a7HAZD WX INFO FOR LAX AREA AVBL FM FLT WATCH. USE CAUTION FOR^\u00a7HANG GLIDING 1 MILE SOUTH LOS ANGELES VOR. NEW WAKE TURBULENCE^\u00a7SEPARATION PROCEDURES IN EFFECT. INCLUDE YOUR CALL SIGN IN ALL^\u00a7REED BACKS. UPON RECEIPT OF YOUR ATC CLNC REED BACK ONLY YOUR^\u00a7SQUAWK CODE....ADVS YOU HAVE INFO D.",
      "planned_route": "",
      "planned_tascruise": "0",
      "callsign": "KLAX_ATIS",
      "transponder": "",
      "heading": "",
      "clienttype": "ATC",
      "visualrange": "0",
      "latitude": "33.94250",
      "planned_minfuel": "",
      "facilitytype": "4",
      "planned_hrsenroute": "",
      "planned_aircraft": "",
      "longitude": "-118.40807",
      "frequency": "133.800",
      "time_logon": "20161015232041",
      "planned_destairport": "",
      "groundspeed": "",
      "planned_flighttype": "",
      "planned_depairport_lat": "",
      "altitude": "0",
      "planned_altairport": "",
      "server": "USA-W",
      "cid": "1308359",
      "planned_destairport_lat": "",
      "QNH_Mb": "",
      "planned_depairport_lon": "",
      "planned_actdeptime": "",
      "planned_revision": ""
    },
    {
      "QNH_iHg": "",
      "planned_deptime": "",
      "planned_destairport_lon": "",
      "planned_altitude": "",
      "time_last_atis_received": "20161015231704",
      "planned_hrsfuel": "",
      "rating": "3",
      "planned_depairport": "",
      "realname": "Jeffrey Sydenham",
      "planned_minenroute": "",
      "protrevision": "100",
      "planned_remarks": "",
      "atis_message": "$ rw.liveatc.net/KLIT_ATIS^\u00a7LIT ATIS INFO T 2253Z. 17006KT 10SM FEW040 FEW100 FEW250 25/19^\u00a7A3001 (THREE ZERO ZERO ONE). LANDING AND DEPARTING RUNWAYS 22L^\u00a7AND 22R. ILS AND VISUAL APPROACHES IN USE.. SIMULTANEOUS^\u00a7APPROACHES TO PARALLEL RUNWAYS IN USE. . ...ADVS YOU HAVE INFO^\u00a7T.",
      "planned_route": "",
      "planned_tascruise": "0",
      "callsign": "KLIT_ATIS",
      "transponder": "",
      "heading": "",
      "clienttype": "ATC",
      "visualrange": "0",
      "latitude": "34.72945",
      "planned_minfuel": "",
      "facilitytype": "4",
      "planned_hrsenroute": "",
      "planned_aircraft": "",
      "longitude": "-92.22478",
      "frequency": "125.650",
      "time_logon": "20161015221544",
      "planned_destairport": "",
      "groundspeed": "",
      "planned_flighttype": "",
      "planned_depairport_lat": "",
      "altitude": "0",
      "planned_altairport": "",
      "server": "UK2",
      "cid": "1350554",
      "planned_destairport_lat": "",
      "QNH_Mb": "",
      "planned_depairport_lon": "",
      "planned_actdeptime": "",
      "planned_revision": ""
    },
    {
      "QNH_iHg": "",
      "planned_deptime": "",
      "planned_destairport_lon": "",
      "planned_altitude": "",
      "time_last_atis_received": "20161015232340",
      "planned_hrsfuel": "",
      "rating": "8",
      "planned_depairport": "",
      "realname": "Andrew James Doubleday",
      "planned_minenroute": "",
      "protrevision": "100",
      "planned_remarks": "",
      "atis_message": "$ vhf.minniecenter.org/KMSP_ATIS^\u00a7MSP ATIS INFO A 2253Z. 29007KT 10SM -RA FEW030 SCT100 OVC150^\u00a718/13 A2974 (TWO NINER SEVEN FOUR). VIS RWY 30L APCH IN USE, VIS^\u00a7RWY 30R APCH IN USE. DEPTG RWY 30L, RWY 30R, RWY 17. CAUTION,^\u00a7MIGRATING WATERFOWL IN VCNTY KMSP. READ BACK HS INSTRUCTIONS AND^\u00a7ASSIGNED ALTS.. ALL ACFT TAXI WITH XPDR AND ALT ENCODING ON.^\u00a7...ADVS YOU HAVE INFO A",
      "planned_route": "",
      "planned_tascruise": "0",
      "callsign": "KMSP_ATIS",
      "transponder": "",
      "heading": "",
      "clienttype": "ATC",
      "visualrange": "0",
      "latitude": "44.88197",
      "planned_minfuel": "",
      "facilitytype": "4",
      "planned_hrsenroute": "",
      "planned_aircraft": "",
      "longitude": "-93.22178",
      "frequency": "135.350",
      "time_logon": "20161015203631",
      "planned_destairport": "",
      "groundspeed": "",
      "planned_flighttype": "",
      "planned_depairport_lat": "",
      "altitude": "0",
      "planned_altairport": "",
      "server": "USA-C",
      "cid": "844751",
      "planned_destairport_lat": "",
      "QNH_Mb": "",
      "planned_depairport_lon": "",
      "planned_actdeptime": "",
      "planned_revision": ""
    },
    {
      "QNH_iHg": "",
      "planned_deptime": "",
      "planned_destairport_lon": "",
      "planned_altitude": "",
      "time_last_atis_received": "20161015232125",
      "planned_hrsfuel": "",
      "rating": "3",
      "planned_depairport": "",
      "realname": "Andrew Zane",
      "planned_minenroute": "",
      "protrevision": "100",
      "planned_remarks": "",
      "atis_message": "$ voice.radarcontact.me/KOAK_ATIS^\u00a7KOAK info LIMA 152253Z winds 180 at 20 gust 25 visibility 10SM^\u00a7Sky conditions BKN041 BKN050 BKN130 temp 21 dewpt 16 altimeter 2981^\u00a7Read back all hold short instructions. Advise you have info LIMA.",
      "planned_route": "",
      "planned_tascruise": "0",
      "callsign": "KOAK_ATIS",
      "transponder": "",
      "heading": "",
      "clienttype": "ATC",
      "visualrange": "0",
      "latitude": "37.72126",
      "planned_minfuel": "",
      "facilitytype": "4",
      "planned_hrsenroute": "",
      "planned_aircraft": "",
      "longitude": "-122.22115",
      "frequency": "133.770",
      "time_logon": "20161015222031",
      "planned_destairport": "",
      "groundspeed": "",
      "planned_flighttype": "",
      "planned_depairport_lat": "",
      "altitude": "0",
      "planned_altairport": "",
      "server": "USA-C2",
      "cid": "1365112",
      "planned_destairport_lat": "",
      "QNH_Mb": "",
      "planned_depairport_lon": "",
      "planned_actdeptime": "",
      "planned_revision": ""
    },
    {
      "QNH_iHg": "",
      "planned_deptime": "",
      "planned_destairport_lon": "",
      "planned_altitude": "",
      "time_last_atis_received": "20161015231040",
      "planned_hrsfuel": "",
      "rating": "5",
      "planned_depairport": "",
      "realname": "Jakob Kruse",
      "planned_minenroute": "",
      "protrevision": "100",
      "planned_remarks": "",
      "atis_message": "$ rw.liveatc.net/KPHL_ATIS^\u00a7PHL ATIS INFO H 2254Z. 20006KT 10SM FEW040 FEW250 17/09 A3034^\u00a7(THREE ZERO THREE FOUR). DEPG RWY 27L, RWY 35. SIMUL APCHS IN^\u00a7USE TO INTERSECTI NG RWYS 27 RIGHT AND 35. ARRIVALS EXPECT ILS^\u00a7APCH RWY 27R, OR VISUAL APPROACH RWY 35. NOTAMS... DME RWY 27L^\u00a7OTS, DME RWY 27R OTS, RY 35 PAPI OTS. TWY K3 CLSD BTN RWY 27R^\u00a7AND TWY K ., TWY M CLSD .. ACFT USING RY 27L CTC TWR 135.1. ALL^\u00a7OTHER ACFT USE FREQ 118.5. ADZ GATE ASSIGNMENT TO APPROACH CTL^\u00a7ON INITIAL CTC....ADVS YOU HAVE INFO H.",
      "planned_route": "",
      "planned_tascruise": "0",
      "callsign": "KPHL_ATIS",
      "transponder": "",
      "heading": "",
      "clienttype": "ATC",
      "visualrange": "0",
      "latitude": "39.87225",
      "planned_minfuel": "",
      "facilitytype": "4",
      "planned_hrsenroute": "",
      "planned_aircraft": "",
      "longitude": "-75.24087",
      "frequency": "133.400",
      "time_logon": "20161015224002",
      "planned_destairport": "",
      "groundspeed": "",
      "planned_flighttype": "",
      "planned_depairport_lat": "",
      "altitude": "0",
      "planned_altairport": "",
      "server": "USA-E",
      "cid": "1309208",
      "planned_destairport_lat": "",
      "QNH_Mb": "",
      "planned_depairport_lon": "",
      "planned_actdeptime": "",
      "planned_revision": ""
    },
    {
      "QNH_iHg": "",
      "planned_deptime": "",
      "planned_destairport_lon": "",
      "planned_altitude": "",
      "time_last_atis_received": "20161015231730",
      "planned_hrsfuel": "",
      "rating": "5",
      "planned_depairport": "",
      "realname": "Gene Cao",
      "planned_minenroute": "",
      "protrevision": "100",
      "planned_remarks": "",
      "atis_message": "$ rw.liveatc.net/ksfo_atis^\u00a7SFO ATIS INFO J 2256Z. 20019G23KT 10SM FEW017 BKN028 BKN039^\u00a721/15 A2980 (TWO NINER EIGHT ZERO). SIMULTANEOUS ILS RUNWAY 19L,^\u00a7VISUAL APPROACH IN USE. LANDING RUNWAY 19L, 19R. DEPARTING^\u00a7RUNWAY 10L, 10R. DEPARTING AIRCRAFT NEED TO GET NUMBERS FOR BOTH^\u00a7RUNWAYS 10L AT SIERRA 4 AND 10R AT SIERRA. ASSC SYSTEM IN USE,^\u00a7ACTIVATE TRANSPONDER WITH MODE C ON ALL TWYS AND RWYS. REEDBACK^\u00a7OF ALL RUNWAY HOLDING INSTRUCTIONS IS REQUIRED. ALL AIRCRAFT ARE^\u00a7REQUIRED TO INCLUDE AIRCRAFT CALLSIGNS IN ALL REEDBACKS AND^\u00a7ACKNOWLEDGEMENTS OF ATC INSTRUCTIONS AND CLEARANCES. ADVS YOU^\u00a7HAVE INFO J.",
      "planned_route": "",
      "planned_tascruise": "0",
      "callsign": "KSFO_ATIS",
      "transponder": "",
      "heading": "",
      "clienttype": "ATC",
      "visualrange": "0",
      "latitude": "37.61882",
      "planned_minfuel": "",
      "facilitytype": "4",
      "planned_hrsenroute": "",
      "planned_aircraft": "",
      "longitude": "-122.37543",
      "frequency": "118.850",
      "time_logon": "20161015220122",
      "planned_destairport": "",
      "groundspeed": "",
      "planned_flighttype": "",
      "planned_depairport_lat": "",
      "altitude": "0",
      "planned_altairport": "",
      "server": "USA-C",
      "cid": "1100087",
      "planned_destairport_lat": "",
      "QNH_Mb": "",
      "planned_depairport_lon": "",
      "planned_actdeptime": "",
      "planned_revision": ""
    },
    {
      "QNH_iHg": "",
      "planned_deptime": "",
      "planned_destairport_lon": "",
      "planned_altitude": "",
      "time_last_atis_received": "20161015232312",
      "planned_hrsfuel": "",
      "rating": "3",
      "planned_depairport": "",
      "realname": "Matthew Fox",
      "planned_minenroute": "",
      "protrevision": "100",
      "planned_remarks": "",
      "atis_message": "$ rw.liveatc.net/KSTL_ATIS^\u00a7STL ATIS INFO D 2251Z. 18010KT 10SM FEW070 BKN250 25/16 A2997^\u00a7(TWO NINER NINER SEVEN). ILS RY 12R, ILS RY 11 APCH IN USE, DEPG^\u00a7RY 12L. NOTAMS... TWY E CLSD BTN TWY J AND TWY H . TWY J CLSD^\u00a7BTN TWY R AND RWY 30L .. RWY 30L GS OTS, ILS RWY 12R OM OTS.^\u00a7BIRD ADVISORIES IN EFFECT. USE CAUTION FOR PERSONNEL AND EQUIP^\u00a7ADJ TO RWYS AND TWYS. CPDLC SERVICE AVAILABLE....ADVS YOU HAVE^\u00a7INFO D.",
      "planned_route": "",
      "planned_tascruise": "0",
      "callsign": "KSTL_ATIS",
      "transponder": "",
      "heading": "",
      "clienttype": "ATC",
      "visualrange": "0",
      "latitude": "38.74870",
      "planned_minfuel": "",
      "facilitytype": "4",
      "planned_hrsenroute": "",
      "planned_aircraft": "",
      "longitude": "-90.37003",
      "frequency": "125.025",
      "time_logon": "20161015223726",
      "planned_destairport": "",
      "groundspeed": "",
      "planned_flighttype": "",
      "planned_depairport_lat": "",
      "altitude": "0",
      "planned_altairport": "",
      "server": "USA-C",
      "cid": "1280077",
      "planned_destairport_lat": "",
      "QNH_Mb": "",
      "planned_depairport_lon": "",
      "planned_actdeptime": "",
      "planned_revision": ""
    },
    {
      "QNH_iHg": "",
      "planned_deptime": "",
      "planned_destairport_lon": "",
      "planned_altitude": "",
      "time_last_atis_received": "20161015231940",
      "planned_hrsfuel": "",
      "rating": "3",
      "planned_depairport": "",
      "realname": "Ryan Biehl",
      "planned_minenroute": "",
      "protrevision": "100",
      "planned_remarks": "",
      "atis_message": "Los Angeles Tower at your service^\u00a7Thanks for flying ZLA!^\u00a7How am I doing? laartcc.org/feedback (Initials RB)^\u00a7Any questions? Feel free to send me a private message.^\u00a7Charts and more @ laartcc.org",
      "planned_route": "",
      "planned_tascruise": "0",
      "callsign": "LAX_S_TWR",
      "transponder": "",
      "heading": "",
      "clienttype": "ATC",
      "visualrange": "50",
      "latitude": "33.93663",
      "planned_minfuel": "",
      "facilitytype": "4",
      "planned_hrsenroute": "",
      "planned_aircraft": "",
      "longitude": "-118.39247",
      "frequency": "120.950",
      "time_logon": "20161015231937",
      "planned_destairport": "",
      "groundspeed": "",
      "planned_flighttype": "",
      "planned_depairport_lat": "",
      "altitude": "0",
      "planned_altairport": "",
      "server": "USA-W",
      "cid": "1308359",
      "planned_destairport_lat": "",
      "QNH_Mb": "",
      "planned_depairport_lon": "",
      "planned_actdeptime": "",
      "planned_revision": ""
    },
    {
      "QNH_iHg": "",
      "planned_deptime": "",
      "planned_destairport_lon": "",
      "planned_altitude": "",
      "time_last_atis_received": "20161015231612",
      "planned_hrsfuel": "",
      "rating": "3",
      "planned_depairport": "",
      "realname": "Jeffrey Sydenham",
      "planned_minenroute": "",
      "protrevision": "100",
      "planned_remarks": "",
      "atis_message": "$ rw.liveatc.net/lit_w_app^\u00a7Little Rock Approach^\u00a7Atis on 125.650^\u00a7Feedback at vzme.org/pilotfeedback.php",
      "planned_route": "",
      "planned_tascruise": "0",
      "callsign": "LIT_APP",
      "transponder": "",
      "heading": "",
      "clienttype": "ATC",
      "visualrange": "150",
      "latitude": "34.72944",
      "planned_minfuel": "",
      "facilitytype": "5",
      "planned_hrsenroute": "",
      "planned_aircraft": "",
      "longitude": "-92.22478",
      "frequency": "119.500",
      "time_logon": "20161015221457",
      "planned_destairport": "",
      "groundspeed": "",
      "planned_flighttype": "",
      "planned_depairport_lat": "",
      "altitude": "0",
      "planned_altairport": "",
      "server": "UK1",
      "cid": "1350554",
      "planned_destairport_lat": "",
      "QNH_Mb": "",
      "planned_depairport_lon": "",
      "planned_actdeptime": "",
      "planned_revision": ""
    },
    {
      "QNH_iHg": "",
      "planned_deptime": "",
      "planned_destairport_lon": "",
      "planned_altitude": "",
      "time_last_atis_received": "20161015231157",
      "planned_hrsfuel": "",
      "rating": "3",
      "planned_depairport": "",
      "realname": "Chaz Watkins",
      "planned_minenroute": "",
      "protrevision": "100",
      "planned_remarks": "",
      "atis_message": "$ rw.liveatc.net/lit_twr",
      "planned_route": "",
      "planned_tascruise": "0",
      "callsign": "LIT_TWR",
      "transponder": "",
      "heading": "",
      "clienttype": "ATC",
      "visualrange": "100",
      "latitude": "34.72944",
      "planned_minfuel": "",
      "facilitytype": "4",
      "planned_hrsenroute": "",
      "planned_aircraft": "",
      "longitude": "-92.22478",
      "frequency": "118.700",
      "time_logon": "20161015225639",
      "planned_destairport": "",
      "groundspeed": "",
      "planned_flighttype": "",
      "planned_depairport_lat": "",
      "altitude": "0",
      "planned_altairport": "",
      "server": "USA-E",
      "cid": "1364352",
      "planned_destairport_lat": "",
      "QNH_Mb": "",
      "planned_depairport_lon": "",
      "planned_actdeptime": "",
      "planned_revision": ""
    },
    {
      "QNH_iHg": "",
      "planned_deptime": "",
      "planned_destairport_lon": "",
      "planned_altitude": "",
      "time_last_atis_received": "20161015232033",
      "planned_hrsfuel": "",
      "rating": "7",
      "planned_depairport": "",
      "realname": "Kyle Watkins",
      "planned_minenroute": "",
      "protrevision": "100",
      "planned_remarks": "",
      "atis_message": "$ rw.liveatc.net/lmt_app^\u00a7Kingsley Approach",
      "planned_route": "",
      "planned_tascruise": "0",
      "callsign": "LMT_APP",
      "transponder": "",
      "heading": "",
      "clienttype": "ATC",
      "visualrange": "150",
      "latitude": "42.15793",
      "planned_minfuel": "",
      "facilitytype": "5",
      "planned_hrsenroute": "",
      "planned_aircraft": "",
      "longitude": "-121.67469",
      "frequency": "123.675",
      "time_logon": "20161015223502",
      "planned_destairport": "",
      "groundspeed": "",
      "planned_flighttype": "",
      "planned_depairport_lat": "",
      "altitude": "0",
      "planned_altairport": "",
      "server": "USA-W",
      "cid": "1151068",
      "planned_destairport_lat": "",
      "QNH_Mb": "",
      "planned_depairport_lon": "",
      "planned_actdeptime": "",
      "planned_revision": ""
    },
    {
      "QNH_iHg": "",
      "planned_deptime": "",
      "planned_destairport_lon": "",
      "planned_altitude": "",
      "time_last_atis_received": "20161015232245",
      "planned_hrsfuel": "",
      "rating": "5",
      "planned_depairport": "",
      "realname": "Filip Markoski",
      "planned_minenroute": "",
      "protrevision": "100",
      "planned_remarks": "",
      "atis_message": "$ voice.vroute.net/lwss_ctr^\u00a7Skopje Radar^\u00a7LWSK ATIS 130.12^\u00a7Charts and sceneries on www.macvacc.org",
      "planned_route": "",
      "planned_tascruise": "0",
      "callsign": "LWSS_CTR",
      "transponder": "",
      "heading": "",
      "clienttype": "ATC",
      "visualrange": "250",
      "latitude": "41.64333",
      "planned_minfuel": "",
      "facilitytype": "6",
      "planned_hrsenroute": "",
      "planned_aircraft": "",
      "longitude": "21.77083",
      "frequency": "119.370",
      "time_logon": "20161015232228",
      "planned_destairport": "",
      "groundspeed": "",
      "planned_flighttype": "",
      "planned_depairport_lat": "",
      "altitude": "0",
      "planned_altairport": "",
      "server": "GERMANY",
      "cid": "1096476",
      "planned_destairport_lat": "",
      "QNH_Mb": "",
      "planned_depairport_lon": "",
      "planned_actdeptime": "",
      "planned_revision": ""
    },
    {
      "QNH_iHg": "",
      "planned_deptime": "",
      "planned_destairport_lon": "",
      "planned_altitude": "",
      "time_last_atis_received": "20161015232527",
      "planned_hrsfuel": "",
      "rating": "5",
      "planned_depairport": "",
      "realname": "Dru Klumper",
      "planned_minenroute": "",
      "protrevision": "100",
      "planned_remarks": "",
      "atis_message": "$ rw1.vatpac.org/ml-bik_ctr^\u00a7Sydney Atis on 126.250^\u00a7SY VOR has been Decomission replace it with TESAT^\u00a7covering to YMML ",
      "planned_route": "",
      "planned_tascruise": "0",
      "callsign": "ML-BIK_CTR",
      "transponder": "",
      "heading": "",
      "clienttype": "ATC",
      "visualrange": "500",
      "latitude": "-34.81291",
      "planned_minfuel": "",
      "facilitytype": "6",
      "planned_hrsenroute": "",
      "planned_aircraft": "",
      "longitude": "149.72212",
      "frequency": "125.000",
      "time_logon": "20161015213832",
      "planned_destairport": "",
      "groundspeed": "",
      "planned_flighttype": "",
      "planned_depairport_lat": "",
      "altitude": "0",
      "planned_altairport": "",
      "server": "AUSTRALIA",
      "cid": "1279572",
      "planned_destairport_lat": "",
      "QNH_Mb": "",
      "planned_depairport_lon": "",
      "planned_actdeptime": "",
      "planned_revision": ""
    },
    {
      "QNH_iHg": "",
      "planned_deptime": "",
      "planned_destairport_lon": "",
      "planned_altitude": "",
      "time_last_atis_received": "20161015232340",
      "planned_hrsfuel": "",
      "rating": "8",
      "planned_depairport": "",
      "realname": "Andrew James Doubleday",
      "planned_minenroute": "",
      "protrevision": "100",
      "planned_remarks": "",
      "atis_message": "$ vhf.minniecenter.org/zmp_133.40^\u00a7Minneapolis Center - All Class B, C and D services provided during pulished hours of operation. Reference airnav.^\u00a7Aviate, Navigate, then Communicate. When available, Please check ATIS information for departure/desination runway, weather, and NOTAMs, expect runway assignment in terminal environment.^\u00a7FAA air traffic control graduate at your services. ERAM client in use - services limited by accurate radar simulation. Feedback available at feedback.minniecenter.org. See the other side  twitch.tv/ground_point_niner. All video/audio recorded and logged. Expected Logoff time 0400z.",
      "planned_route": "",
      "planned_tascruise": "0",
      "callsign": "MSP_11_CTR",
      "transponder": "",
      "heading": "",
      "clienttype": "ATC",
      "visualrange": "250",
      "latitude": "47.39781",
      "planned_minfuel": "",
      "facilitytype": "6",
      "planned_hrsenroute": "",
      "planned_aircraft": "",
      "longitude": "-93.17055",
      "frequency": "133.400",
      "time_logon": "20161015203616",
      "planned_destairport": "",
      "groundspeed": "",
      "planned_flighttype": "",
      "planned_depairport_lat": "",
      "altitude": "0",
      "planned_altairport": "",
      "server": "USA-W",
      "cid": "844751",
      "planned_destairport_lat": "",
      "QNH_Mb": "",
      "planned_depairport_lon": "",
      "planned_actdeptime": "",
      "planned_revision": ""
    },
    {
      "QNH_iHg": "",
      "planned_deptime": "",
      "planned_destairport_lon": "",
      "planned_altitude": "",
      "time_last_atis_received": "20161015231521",
      "planned_hrsfuel": "",
      "rating": "8",
      "planned_depairport": "",
      "realname": "Ryan Parry",
      "planned_minenroute": "",
      "protrevision": "100",
      "planned_remarks": "",
      "atis_message": "NCT_I_APP^\u00a7Providing service for KSFO, KOAK, KSJC, KMRY, KSMF and KMOD plus the surrounding airports.^\u00a7Pilots, read our Letter to Airmen here http //goo.gl/zpLMya",
      "planned_route": "",
      "planned_tascruise": "0",
      "callsign": "NCT_I_APP",
      "transponder": "",
      "heading": "",
      "clienttype": "ATC",
      "visualrange": "150",
      "latitude": "37.76343",
      "planned_minfuel": "",
      "facilitytype": "5",
      "planned_hrsenroute": "",
      "planned_aircraft": "",
      "longitude": "-122.26545",
      "frequency": "199.998",
      "time_logon": "20161015222919",
      "planned_destairport": "",
      "groundspeed": "",
      "planned_flighttype": "",
      "planned_depairport_lat": "",
      "altitude": "0",
      "planned_altairport": "",
      "server": "USA-W",
      "cid": "965346",
      "planned_destairport_lat": "",
      "QNH_Mb": "",
      "planned_depairport_lon": "",
      "planned_actdeptime": "",
      "planned_revision": ""
    },
    {
      "QNH_iHg": "",
      "planned_deptime": "",
      "planned_destairport_lon": "",
      "planned_altitude": "",
      "time_last_atis_received": "20161015231521",
      "planned_hrsfuel": "",
      "rating": "4",
      "planned_depairport": "",
      "realname": "Elliot Skinner",
      "planned_minenroute": "",
      "protrevision": "100",
      "planned_remarks": "",
      "atis_message": "$ voice.radarcontact.me/SFO_APP^\u00a7Norcal Approach NorCal Combined, controlling SFO, OAK, SJC, MRY, SMF, MOD, and surrounding airports.",
      "planned_route": "",
      "planned_tascruise": "0",
      "callsign": "NCT_S_APP",
      "transponder": "",
      "heading": "",
      "clienttype": "ATC",
      "visualrange": "150",
      "latitude": "37.61881",
      "planned_minfuel": "",
      "facilitytype": "5",
      "planned_hrsenroute": "",
      "planned_aircraft": "",
      "longitude": "-122.37542",
      "frequency": "135.650",
      "time_logon": "20161015222913",
      "planned_destairport": "",
      "groundspeed": "",
      "planned_flighttype": "",
      "planned_depairport_lat": "",
      "altitude": "0",
      "planned_altairport": "",
      "server": "USA-W",
      "cid": "1210194",
      "planned_destairport_lat": "",
      "QNH_Mb": "",
      "planned_depairport_lon": "",
      "planned_actdeptime": "",
      "planned_revision": ""
    },
    {
      "QNH_iHg": "",
      "planned_deptime": "",
      "planned_destairport_lon": "",
      "planned_altitude": "",
      "time_last_atis_received": "",
      "planned_hrsfuel": "",
      "rating": "1",
      "planned_depairport": "",
      "realname": "Andy Joy",
      "planned_minenroute": "",
      "protrevision": "100",
      "planned_remarks": "",
      "atis_message": "",
      "planned_route": "",
      "planned_tascruise": "0",
      "callsign": "NGE255A",
      "transponder": "",
      "heading": "",
      "clienttype": "ATC",
      "visualrange": "100",
      "latitude": "65.41290",
      "planned_minfuel": "",
      "facilitytype": "0",
      "planned_hrsenroute": "",
      "planned_aircraft": "",
      "longitude": "13.03783",
      "frequency": "199.998",
      "time_logon": "20161015204407",
      "planned_destairport": "",
      "groundspeed": "",
      "planned_flighttype": "",
      "planned_depairport_lat": "",
      "altitude": "0",
      "planned_altairport": "",
      "server": "UK1",
      "cid": "1319125",
      "planned_destairport_lat": "",
      "QNH_Mb": "",
      "planned_depairport_lon": "",
      "planned_actdeptime": "",
      "planned_revision": ""
    },
    {
      "QNH_iHg": "",
      "planned_deptime": "",
      "planned_destairport_lon": "",
      "planned_altitude": "",
      "time_last_atis_received": "20161015232527",
      "planned_hrsfuel": "",
      "rating": "8",
      "planned_depairport": "",
      "realname": "Jakob Kruse",
      "planned_minenroute": "",
      "protrevision": "100",
      "planned_remarks": "",
      "atis_message": "$ voice.nyartcc.org/ZNY_B4^\u00a7New York Center^\u00a7Serving all ZNY sectors including PHL TRACON (no oceanic)^\u00a7Class D tower services provided workload permitting^\u00a7Pilot Resources - nyartcc.org",
      "planned_route": "",
      "planned_tascruise": "0",
      "callsign": "NY_CTR",
      "transponder": "",
      "heading": "",
      "clienttype": "ATC",
      "visualrange": "300",
      "latitude": "42.15991",
      "planned_minfuel": "",
      "facilitytype": "6",
      "planned_hrsenroute": "",
      "planned_aircraft": "",
      "longitude": "-76.89144",
      "frequency": "125.320",
      "time_logon": "20161015223928",
      "planned_destairport": "",
      "groundspeed": "",
      "planned_flighttype": "",
      "planned_depairport_lat": "",
      "altitude": "0",
      "planned_altairport": "",
      "server": "USA-E",
      "cid": "1309208",
      "planned_destairport_lat": "",
      "QNH_Mb": "",
      "planned_depairport_lon": "",
      "planned_actdeptime": "",
      "planned_revision": ""
    },
    {
      "QNH_iHg": "",
      "planned_deptime": "",
      "planned_destairport_lon": "",
      "planned_altitude": "",
      "time_last_atis_received": "20161015231705",
      "planned_hrsfuel": "",
      "rating": "5",
      "planned_depairport": "",
      "realname": "Oliver Holmwood",
      "planned_minenroute": "",
      "protrevision": "100",
      "planned_remarks": "",
      "atis_message": "$ rw1.vatpac.org/nzch-t_ctr^\u00a7Christchurch Control - 123.700^\u00a7Charts- www.vatnz.net/airspace/airports^\u00a7Extending Raglan, Bay, Ohakea.",
      "planned_route": "",
      "planned_tascruise": "0",
      "callsign": "NZCH-T_CTR",
      "transponder": "",
      "heading": "",
      "clienttype": "ATC",
      "visualrange": "600",
      "latitude": "-41.33722",
      "planned_minfuel": "",
      "facilitytype": "6",
      "planned_hrsenroute": "",
      "planned_aircraft": "",
      "longitude": "174.81697",
      "frequency": "123.700",
      "time_logon": "20161015231642",
      "planned_destairport": "",
      "groundspeed": "",
      "planned_flighttype": "",
      "planned_depairport_lat": "",
      "altitude": "0",
      "planned_altairport": "",
      "server": "AUSTRALIA",
      "cid": "1312734",
      "planned_destairport_lat": "",
      "QNH_Mb": "",
      "planned_depairport_lon": "",
      "planned_actdeptime": "",
      "planned_revision": ""
    },
    {
      "QNH_iHg": "",
      "planned_deptime": "",
      "planned_destairport_lon": "",
      "planned_altitude": "",
      "time_last_atis_received": "20161015231730",
      "planned_hrsfuel": "",
      "rating": "5",
      "planned_depairport": "",
      "realname": "Oliver Holmwood",
      "planned_minenroute": "",
      "protrevision": "100",
      "planned_remarks": "",
      "atis_message": "$ rw1.vatpac.org/nzwn_atis^\u00a7WELLINGTON INFORMATION QUEBEC issued at 2300^\u00a7expect ILS approach RWY 34 surface condition dry surface wind^\u00a7010 at 16 visibility more than 10 kilometers CLD SCT 3100 FT^\u00a7TMP 16 DP 10 QNH 1010 on first contact with WELLINGTON ground^\u00a7or tower notify receipt of QUEBEC",
      "planned_route": "",
      "planned_tascruise": "0",
      "callsign": "NZWN_ATIS",
      "transponder": "",
      "heading": "",
      "clienttype": "ATC",
      "visualrange": "0",
      "latitude": "-41.32722",
      "planned_minfuel": "",
      "facilitytype": "4",
      "planned_hrsenroute": "",
      "planned_aircraft": "",
      "longitude": "174.80528",
      "frequency": "126.900",
      "time_logon": "20161015231725",
      "planned_destairport": "",
      "groundspeed": "",
      "planned_flighttype": "",
      "planned_depairport_lat": "",
      "altitude": "0",
      "planned_altairport": "",
      "server": "AUSTRALIA",
      "cid": "1312734",
      "planned_destairport_lat": "",
      "QNH_Mb": "",
      "planned_depairport_lon": "",
      "planned_actdeptime": "",
      "planned_revision": ""
    },
    {
      "QNH_iHg": "",
      "planned_deptime": "",
      "planned_destairport_lon": "",
      "planned_altitude": "",
      "time_last_atis_received": "20161015231705",
      "planned_hrsfuel": "",
      "rating": "5",
      "planned_depairport": "",
      "realname": "Gene Cao",
      "planned_minenroute": "",
      "protrevision": "100",
      "planned_remarks": "",
      "atis_message": "$ rw.liveatc.net/OAK_CTR^\u00a7Callsign Oakland Center^\u00a7Magic words for Pilots Unable.^\u00a7Aviate, Navigate, then Communicate.^\u00a7Feedback appreciated at oakartcc.com. Thanks for flying ZOA",
      "planned_route": "",
      "planned_tascruise": "0",
      "callsign": "OAK_CTR",
      "transponder": "",
      "heading": "",
      "clienttype": "ATC",
      "visualrange": "340",
      "latitude": "36.14038",
      "planned_minfuel": "",
      "facilitytype": "6",
      "planned_hrsenroute": "",
      "planned_aircraft": "",
      "longitude": "-120.66492",
      "frequency": "132.200",
      "time_logon": "20161015204454",
      "planned_destairport": "",
      "groundspeed": "",
      "planned_flighttype": "",
      "planned_depairport_lat": "",
      "altitude": "0",
      "planned_altairport": "",
      "server": "USA-W",
      "cid": "1100087",
      "planned_destairport_lat": "",
      "QNH_Mb": "",
      "planned_depairport_lon": "",
      "planned_actdeptime": "",
      "planned_revision": ""
    },
    {
      "QNH_iHg": "",
      "planned_deptime": "",
      "planned_destairport_lon": "",
      "planned_altitude": "",
      "time_last_atis_received": "20161015231040",
      "planned_hrsfuel": "",
      "rating": "3",
      "planned_depairport": "",
      "realname": "Andrew Zane",
      "planned_minenroute": "",
      "protrevision": "100",
      "planned_remarks": "",
      "atis_message": "$ voice.radarcontact.me/OAK_TWR^\u00a7Oakland Tower^\u00a7Information KILO Winds 180 at 20 gust 25 Vis 10SM Sky BKN041 BKN050 BKN130 Alt 2981",
      "planned_route": "",
      "planned_tascruise": "0",
      "callsign": "OAK_TWR",
      "transponder": "",
      "heading": "",
      "clienttype": "ATC",
      "visualrange": "50",
      "latitude": "37.71259",
      "planned_minfuel": "",
      "facilitytype": "4",
      "planned_hrsenroute": "",
      "planned_aircraft": "",
      "longitude": "-122.21773",
      "frequency": "127.200",
      "time_logon": "20161015220935",
      "planned_destairport": "",
      "groundspeed": "",
      "planned_flighttype": "",
      "planned_depairport_lat": "",
      "altitude": "0",
      "planned_altairport": "",
      "server": "USA-C2",
      "cid": "1365112",
      "planned_destairport_lat": "",
      "QNH_Mb": "",
      "planned_depairport_lon": "",
      "planned_actdeptime": "",
      "planned_revision": ""
    },
    {
      "QNH_iHg": "",
      "planned_deptime": "",
      "planned_destairport_lon": "",
      "planned_altitude": "",
      "time_last_atis_received": "",
      "planned_hrsfuel": "",
      "rating": "1",
      "planned_depairport": "",
      "realname": "Eugen Sch nung - LOWW",
      "planned_minenroute": "",
      "protrevision": "100",
      "planned_remarks": "",
      "atis_message": "",
      "planned_route": "",
      "planned_tascruise": "0",
      "callsign": "OE-LTM",
      "transponder": "",
      "heading": "",
      "clienttype": "ATC",
      "visualrange": "30",
      "latitude": "47.66927",
      "planned_minfuel": "",
      "facilitytype": "0",
      "planned_hrsenroute": "",
      "planned_aircraft": "",
      "longitude": "9.51277",
      "frequency": "119.920",
      "time_logon": "20161015220612",
      "planned_destairport": "",
      "groundspeed": "",
      "planned_flighttype": "",
      "planned_depairport_lat": "",
      "altitude": "0",
      "planned_altairport": "",
      "server": "GERMANY",
      "cid": "932750",
      "planned_destairport_lat": "",
      "QNH_Mb": "",
      "planned_depairport_lon": "",
      "planned_actdeptime": "",
      "planned_revision": ""
    },
    {
      "QNH_iHg": "",
      "planned_deptime": "",
      "planned_destairport_lon": "",
      "planned_altitude": "",
      "time_last_atis_received": "20161015231156",
      "planned_hrsfuel": "",
      "rating": "2",
      "planned_depairport": "",
      "realname": "Michael Lac",
      "planned_minenroute": "",
      "protrevision": "100",
      "planned_remarks": "",
      "atis_message": "$ rw.liveatc.net/ojai_gnd^\u00a7Queen Alia Ground^\u00a7Landing and Departing 26L^\u00a7Charts and Info visit  - vatjo.net -",
      "planned_route": "",
      "planned_tascruise": "0",
      "callsign": "OJAI_GND",
      "transponder": "",
      "heading": "",
      "clienttype": "ATC",
      "visualrange": "15",
      "latitude": "31.72282",
      "planned_minfuel": "",
      "facilitytype": "3",
      "planned_hrsenroute": "",
      "planned_aircraft": "",
      "longitude": "35.99347",
      "frequency": "121.700",
      "time_logon": "20161015231151",
      "planned_destairport": "",
      "groundspeed": "",
      "planned_flighttype": "",
      "planned_depairport_lat": "",
      "altitude": "0",
      "planned_altairport": "",
      "server": "UK1",
      "cid": "1333227",
      "planned_destairport_lat": "",
      "QNH_Mb": "",
      "planned_depairport_lon": "",
      "planned_actdeptime": "",
      "planned_revision": ""
    },
    {
      "QNH_iHg": "",
      "planned_deptime": "",
      "planned_destairport_lon": "",
      "planned_altitude": "",
      "time_last_atis_received": "",
      "planned_hrsfuel": "",
      "rating": "3",
      "planned_depairport": "",
      "realname": "Kyran Erwin",
      "planned_minenroute": "",
      "protrevision": "100",
      "planned_remarks": "",
      "atis_message": "",
      "planned_route": "",
      "planned_tascruise": "0",
      "callsign": "PDX_TWR",
      "transponder": "",
      "heading": "",
      "clienttype": "ATC",
      "visualrange": "50",
      "latitude": "45.58739",
      "planned_minfuel": "",
      "facilitytype": "4",
      "planned_hrsenroute": "",
      "planned_aircraft": "",
      "longitude": "-122.59743",
      "frequency": "123.770",
      "time_logon": "20161015232547",
      "planned_destairport": "",
      "groundspeed": "",
      "planned_flighttype": "",
      "planned_depairport_lat": "",
      "altitude": "0",
      "planned_altairport": "",
      "server": "USA-W",
      "cid": "1319756",
      "planned_destairport_lat": "",
      "QNH_Mb": "",
      "planned_depairport_lon": "",
      "planned_actdeptime": "",
      "planned_revision": ""
    },
    {
      "QNH_iHg": "",
      "planned_deptime": "",
      "planned_destairport_lon": "",
      "planned_altitude": "",
      "time_last_atis_received": "",
      "planned_hrsfuel": "",
      "rating": "2",
      "planned_depairport": "",
      "realname": "Bruno Dias",
      "planned_minenroute": "",
      "protrevision": "100",
      "planned_remarks": "",
      "atis_message": "",
      "planned_route": "",
      "planned_tascruise": "0",
      "callsign": "SBGR_TWR",
      "transponder": "",
      "heading": "",
      "clienttype": "ATC",
      "visualrange": "50",
      "latitude": "-23.43556",
      "planned_minfuel": "",
      "facilitytype": "4",
      "planned_hrsenroute": "",
      "planned_aircraft": "",
      "longitude": "-46.47306",
      "frequency": "132.750",
      "time_logon": "20161015232542",
      "planned_destairport": "",
      "groundspeed": "",
      "planned_flighttype": "",
      "planned_depairport_lat": "",
      "altitude": "0",
      "planned_altairport": "",
      "server": "USA-E",
      "cid": "1370035",
      "planned_destairport_lat": "",
      "QNH_Mb": "",
      "planned_depairport_lon": "",
      "planned_actdeptime": "",
      "planned_revision": ""
    },
    {
      "QNH_iHg": "",
      "planned_deptime": "",
      "planned_destairport_lon": "",
      "planned_altitude": "",
      "time_last_atis_received": "20161015231705",
      "planned_hrsfuel": "",
      "rating": "3",
      "planned_depairport": "",
      "realname": "Alancaster Araujo",
      "planned_minenroute": "",
      "protrevision": "100",
      "planned_remarks": "",
      "atis_message": "Recife Tower^\u00a7Information BRAVO Winds 140 at 12 Vis 9999 Sky SCT023 Alt 1015",
      "planned_route": "",
      "planned_tascruise": "0",
      "callsign": "SBRF_TWR",
      "transponder": "",
      "heading": "",
      "clienttype": "ATC",
      "visualrange": "50",
      "latitude": "-6.79234",
      "planned_minfuel": "",
      "facilitytype": "4",
      "planned_hrsenroute": "",
      "planned_aircraft": "",
      "longitude": "-35.27153",
      "frequency": "118.350",
      "time_logon": "20161015223108",
      "planned_destairport": "",
      "groundspeed": "",
      "planned_flighttype": "",
      "planned_depairport_lat": "",
      "altitude": "0",
      "planned_altairport": "",
      "server": "AUSTRALIA",
      "cid": "1051439",
      "planned_destairport_lat": "",
      "QNH_Mb": "",
      "planned_depairport_lon": "",
      "planned_actdeptime": "",
      "planned_revision": ""
    },
    {
      "QNH_iHg": "",
      "planned_deptime": "",
      "planned_destairport_lon": "",
      "planned_altitude": "",
      "time_last_atis_received": "20161015231403",
      "planned_hrsfuel": "",
      "rating": "4",
      "planned_depairport": "",
      "realname": "peter armstrong",
      "planned_minenroute": "",
      "protrevision": "100",
      "planned_remarks": "",
      "atis_message": "$ rw.liveatc.net/sea_app^\u00a7greetings and welcome.^\u00a7squawk mode Charlie (normal) on all taxiways and runways^\u00a7report if you only have 2 runway scenery on board^\u00a7\"Fly\" then reply . May have to revert to text.^\u00a7Dep = RWY 16L - Arrival = RWY 16C^\u00a7on line until approx. 2300z",
      "planned_route": "",
      "planned_tascruise": "0",
      "callsign": "SEA_APP",
      "transponder": "",
      "heading": "",
      "clienttype": "ATC",
      "visualrange": "150",
      "latitude": "47.44900",
      "planned_minfuel": "",
      "facilitytype": "5",
      "planned_hrsenroute": "",
      "planned_aircraft": "",
      "longitude": "-122.30931",
      "frequency": "125.600",
      "time_logon": "20161015215758",
      "planned_destairport": "",
      "groundspeed": "",
      "planned_flighttype": "",
      "planned_depairport_lat": "",
      "altitude": "0",
      "planned_altairport": "",
      "server": "USA-C",
      "cid": "1230152",
      "planned_destairport_lat": "",
      "QNH_Mb": "",
      "planned_depairport_lon": "",
      "planned_actdeptime": "",
      "planned_revision": ""
    },
    {
      "QNH_iHg": "",
      "planned_deptime": "",
      "planned_destairport_lon": "",
      "planned_altitude": "",
      "time_last_atis_received": "20161015232340",
      "planned_hrsfuel": "",
      "rating": "3",
      "planned_depairport": "",
      "realname": "Marcos Darquea",
      "planned_minenroute": "",
      "protrevision": "100",
      "planned_remarks": "",
      "atis_message": "$ rw.liveatc.net/SEQM_ATIS^\u00a7EQM ATIS INFO C 2300Z. 01008KT 9999 VCSH FEW005 BKN030 16/13^\u00a7Q1024 (ONE ZERO TWO FOUR). APCH IN USE ILS RWY36 AND DEP IN USE^\u00a7RWY36... ...ADVS YOU HAVE INFO C.",
      "planned_route": "",
      "planned_tascruise": "0",
      "callsign": "SEQM_ATIS",
      "transponder": "",
      "heading": "",
      "clienttype": "ATC",
      "visualrange": "0",
      "latitude": "-0.12417",
      "planned_minfuel": "",
      "facilitytype": "4",
      "planned_hrsenroute": "",
      "planned_aircraft": "",
      "longitude": "-78.35445",
      "frequency": "118.900",
      "time_logon": "20161015223749",
      "planned_destairport": "",
      "groundspeed": "",
      "planned_flighttype": "",
      "planned_depairport_lat": "",
      "altitude": "0",
      "planned_altairport": "",
      "server": "USA-E",
      "cid": "1204237",
      "planned_destairport_lat": "",
      "QNH_Mb": "",
      "planned_depairport_lon": "",
      "planned_actdeptime": "",
      "planned_revision": ""
    },
    {
      "QNH_iHg": "",
      "planned_deptime": "",
      "planned_destairport_lon": "",
      "planned_altitude": "",
      "time_last_atis_received": "20161015231914",
      "planned_hrsfuel": "",
      "rating": "3",
      "planned_depairport": "",
      "realname": "Marcos Darquea",
      "planned_minenroute": "",
      "protrevision": "100",
      "planned_remarks": "",
      "atis_message": "$ rw.liveatc.net/seqm_twr",
      "planned_route": "",
      "planned_tascruise": "0",
      "callsign": "SEQM_TWR",
      "transponder": "",
      "heading": "",
      "clienttype": "ATC",
      "visualrange": "50",
      "latitude": "-0.12124",
      "planned_minfuel": "",
      "facilitytype": "4",
      "planned_hrsenroute": "",
      "planned_aircraft": "",
      "longitude": "-78.35444",
      "frequency": "118.100",
      "time_logon": "20161015223356",
      "planned_destairport": "",
      "groundspeed": "",
      "planned_flighttype": "",
      "planned_depairport_lat": "",
      "altitude": "0",
      "planned_altairport": "",
      "server": "USA-E",
      "cid": "1204237",
      "planned_destairport_lat": "",
      "QNH_Mb": "",
      "planned_depairport_lon": "",
      "planned_actdeptime": "",
      "planned_revision": ""
    },
    {
      "QNH_iHg": "",
      "planned_deptime": "",
      "planned_destairport_lon": "",
      "planned_altitude": "",
      "time_last_atis_received": "20161015231757",
      "planned_hrsfuel": "",
      "rating": "3",
      "planned_depairport": "",
      "realname": "Jackson Gilliam",
      "planned_minenroute": "",
      "protrevision": "100",
      "planned_remarks": "",
      "atis_message": "$ voice.radarcontact.me/SFO_TWR^\u00a7San Francisco Tower^\u00a7Thanks for flying ZOA!^\u00a7Feedback? Visit www.oakartcc.com/pilot-feedback/^\u00a7EAST ops please make sure you SID matches departure off the 10s",
      "planned_route": "",
      "planned_tascruise": "0",
      "callsign": "SFO_S_TWR",
      "transponder": "",
      "heading": "",
      "clienttype": "ATC",
      "visualrange": "50",
      "latitude": "37.61051",
      "planned_minfuel": "",
      "facilitytype": "4",
      "planned_hrsenroute": "",
      "planned_aircraft": "",
      "longitude": "-122.36068",
      "frequency": "120.500",
      "time_logon": "20161015230231",
      "planned_destairport": "",
      "groundspeed": "",
      "planned_flighttype": "",
      "planned_depairport_lat": "",
      "altitude": "0",
      "planned_altairport": "",
      "server": "USA-W",
      "cid": "1335177",
      "planned_destairport_lat": "",
      "QNH_Mb": "",
      "planned_depairport_lon": "",
      "planned_actdeptime": "",
      "planned_revision": ""
    },
    {
      "QNH_iHg": "",
      "planned_deptime": "",
      "planned_destairport_lon": "",
      "planned_altitude": "",
      "time_last_atis_received": "20161015231040",
      "planned_hrsfuel": "",
      "rating": "3",
      "planned_depairport": "",
      "realname": "Matthew Fox",
      "planned_minenroute": "",
      "protrevision": "100",
      "planned_remarks": "",
      "atis_message": "$ rw.liveatc.net/STL_APP",
      "planned_route": "",
      "planned_tascruise": "0",
      "callsign": "STL_APP",
      "transponder": "",
      "heading": "",
      "clienttype": "ATC",
      "visualrange": "135",
      "latitude": "38.62250",
      "planned_minfuel": "",
      "facilitytype": "5",
      "planned_hrsenroute": "",
      "planned_aircraft": "",
      "longitude": "-90.11357",
      "frequency": "132.120",
      "time_logon": "20161015210811",
      "planned_destairport": "",
      "groundspeed": "",
      "planned_flighttype": "",
      "planned_depairport_lat": "",
      "altitude": "0",
      "planned_altairport": "",
      "server": "USA-C2",
      "cid": "1280077",
      "planned_destairport_lat": "",
      "QNH_Mb": "",
      "planned_depairport_lon": "",
      "planned_actdeptime": "",
      "planned_revision": ""
    },
    {
      "QNH_iHg": "",
      "planned_deptime": "",
      "planned_destairport_lon": "",
      "planned_altitude": "",
      "time_last_atis_received": "20161015231848",
      "planned_hrsfuel": "",
      "rating": "8",
      "planned_depairport": "",
      "realname": "Kyle Kaestner",
      "planned_minenroute": "",
      "protrevision": "100",
      "planned_remarks": "",
      "atis_message": "STL_I_APP^\u00a7I control KBLV, KSUS, KCPS, KALN^\u00a7KSTL Approach- https //www.twitch.tv/choasmc^\u00a7Thanks for Flying ZKC - http //kcartcc.com/feedback",
      "planned_route": "",
      "planned_tascruise": "0",
      "callsign": "STL_I_APP",
      "transponder": "",
      "heading": "",
      "clienttype": "ATC",
      "visualrange": "150",
      "latitude": "38.74854",
      "planned_minfuel": "",
      "facilitytype": "5",
      "planned_hrsenroute": "",
      "planned_aircraft": "",
      "longitude": "-90.25748",
      "frequency": "199.998",
      "time_logon": "20161015230338",
      "planned_destairport": "",
      "groundspeed": "",
      "planned_flighttype": "",
      "planned_depairport_lat": "",
      "altitude": "0",
      "planned_altairport": "",
      "server": "USA-C",
      "cid": "1330148",
      "planned_destairport_lat": "",
      "QNH_Mb": "",
      "planned_depairport_lon": "",
      "planned_actdeptime": "",
      "planned_revision": ""
    },
    {
      "QNH_iHg": "",
      "planned_deptime": "",
      "planned_destairport_lon": "",
      "planned_altitude": "",
      "time_last_atis_received": "20161015231822",
      "planned_hrsfuel": "",
      "rating": "8",
      "planned_depairport": "",
      "realname": "Roman Savel",
      "planned_minenroute": "",
      "protrevision": "100",
      "planned_remarks": "",
      "atis_message": "$ voice1.vacc-sag.org/umms_atis^\u00a7UMMS ATIS information A 2300 expect ILS VORDME approach runway^\u00a713 departure runway 13 transition level 080 wind 090 degrees 3^\u00a7mps visibility greater than 10 km cloud overcast 900  m^\u00a7temperature 3 dew point 1 QNH 1034 or 775 mm acknowledge^\u00a7information A",
      "planned_route": "",
      "planned_tascruise": "0",
      "callsign": "UMMS_ATIS",
      "transponder": "",
      "heading": "",
      "clienttype": "ATC",
      "visualrange": "0",
      "latitude": "53.88250",
      "planned_minfuel": "",
      "facilitytype": "4",
      "planned_hrsenroute": "",
      "planned_aircraft": "",
      "longitude": "28.03250",
      "frequency": "128.850",
      "time_logon": "20161015175959",
      "planned_destairport": "",
      "groundspeed": "",
      "planned_flighttype": "",
      "planned_depairport_lat": "",
      "altitude": "0",
      "planned_altairport": "",
      "server": "GERMANY",
      "cid": "1077915",
      "planned_destairport_lat": "",
      "QNH_Mb": "",
      "planned_depairport_lon": "",
      "planned_actdeptime": "",
      "planned_revision": ""
    },
    {
      "QNH_iHg": "",
      "planned_deptime": "",
      "planned_destairport_lon": "",
      "planned_altitude": "",
      "time_last_atis_received": "20161015231730",
      "planned_hrsfuel": "",
      "rating": "8",
      "planned_depairport": "",
      "realname": "Roman Savel",
      "planned_minenroute": "",
      "protrevision": "100",
      "planned_remarks": "",
      "atis_message": "$ voice1.vacc-sag.org/ummv_ctr^\u00a7Minsk Control",
      "planned_route": "",
      "planned_tascruise": "0",
      "callsign": "UMMV_CTR",
      "transponder": "",
      "heading": "",
      "clienttype": "ATC",
      "visualrange": "600",
      "latitude": "53.85814",
      "planned_minfuel": "",
      "facilitytype": "6",
      "planned_hrsenroute": "",
      "planned_aircraft": "",
      "longitude": "27.86656",
      "frequency": "129.000",
      "time_logon": "20161015175907",
      "planned_destairport": "",
      "groundspeed": "",
      "planned_flighttype": "",
      "planned_depairport_lat": "",
      "altitude": "0",
      "planned_altairport": "",
      "server": "GERMANY",
      "cid": "1077915",
      "planned_destairport_lat": "",
      "QNH_Mb": "",
      "planned_depairport_lon": "",
      "planned_actdeptime": "",
      "planned_revision": ""
    },
    {
      "QNH_iHg": "",
      "planned_deptime": "",
      "planned_destairport_lon": "",
      "planned_altitude": "",
      "time_last_atis_received": "20161015231731",
      "planned_hrsfuel": "",
      "rating": "12",
      "planned_depairport": "",
      "realname": "Federico Navarro",
      "planned_minenroute": "",
      "protrevision": "100",
      "planned_remarks": "",
      "atis_message": "",
      "planned_route": "",
      "planned_tascruise": "0",
      "callsign": "VATSA1",
      "transponder": "",
      "heading": "",
      "clienttype": "ATC",
      "visualrange": "150",
      "latitude": "15.35756",
      "planned_minfuel": "",
      "facilitytype": "1",
      "planned_hrsenroute": "",
      "planned_aircraft": "",
      "longitude": "-76.43477",
      "frequency": "199.998",
      "time_logon": "20161015223200",
      "planned_destairport": "",
      "groundspeed": "",
      "planned_flighttype": "",
      "planned_depairport_lat": "",
      "altitude": "0",
      "planned_altairport": "",
      "server": "AUSTRALIA",
      "cid": "1013441",
      "planned_destairport_lat": "",
      "QNH_Mb": "",
      "planned_depairport_lon": "",
      "planned_actdeptime": "",
      "planned_revision": ""
    },
    {
      "QNH_iHg": "",
      "planned_deptime": "",
      "planned_destairport_lon": "",
      "planned_altitude": "",
      "time_last_atis_received": "20161015232126",
      "planned_hrsfuel": "",
      "rating": "5",
      "planned_depairport": "",
      "realname": "Dru Klumper",
      "planned_minenroute": "",
      "protrevision": "100",
      "planned_remarks": "",
      "atis_message": "$ rw1.vatpac.org/yssy_atis^\u00a7SYDNEY TERMINAL INFO W , EXP INDEP VIS APCH , CL , RWY 34 L&R^\u00a7FOR ARRS AND DEPS , PARL RWY OPS IN PROG , INDEP DEPS IN PROG ,^\u00a7WND 360 / 14 KT MX XW 6 KT , VIS CAVOK , TMP 2 2, , QNH 101 4, ,^\u00a7FCST MOD TURB BLW 5000 FT , ON FIRST CONTACT WITH SYDNEY^\u00a7NOTIFY RECEIPT W ,",
      "planned_route": "",
      "planned_tascruise": "0",
      "callsign": "YSSY_ATIS",
      "transponder": "",
      "heading": "",
      "clienttype": "ATC",
      "visualrange": "0",
      "latitude": "-33.94611",
      "planned_minfuel": "",
      "facilitytype": "4",
      "planned_hrsenroute": "",
      "planned_aircraft": "",
      "longitude": "151.17722",
      "frequency": "126.250",
      "time_logon": "20161015214937",
      "planned_destairport": "",
      "groundspeed": "",
      "planned_flighttype": "",
      "planned_depairport_lat": "",
      "altitude": "0",
      "planned_altairport": "",
      "server": "AUSTRALIA",
      "cid": "1279572",
      "planned_destairport_lat": "",
      "QNH_Mb": "",
      "planned_depairport_lon": "",
      "planned_actdeptime": "",
      "planned_revision": ""
    }
  ]
}